{"id":"nyira0mp9akxbwg7","createdAt":1720953214129,"updatedAt":1720953228794,"fileModified":0,"width":1920,"height":1080,"type":"images","title":"2024-07-14_12.33.33.png","order":0,"filePath":"/loreforge-project-rixyafry5p0nicv2/image-files/2024-07-14_12.33.33.png","fileName":"2024-07-14_12.33.33.png","text":"","textPreview":"","altTitle":"","link":"","size":3115245,"storyIds":[],"orgIds":[],"flagsOfOrgIds":[],"flagsOfLocationIds":[],"locationIds":[],"characterIds":[],"tagIds":[],"noteIds":[],"thingIds":[],"speciesIds":[],"discIds":[],"cultureIds":[]}