{"age":27,"aliases":"maels","birthplaceId":"z0neecie74opu4jp","category":"main","createdAt":1720963842285,"cultureIds":["htqw0zhpixyn8x4u"],"discPioneerIds":[],"discUserIds":[],"firstName":"Sans","gender":"Male","graphIds":[],"id":"nll7ze8ex7js9lw7","imageIds":["3km8fabtjbjpk5uo"],"infoTabs":[{"isEmpty":true,"label":"Appearance","placeholder":"Physique, unique anatomical features, skin/feather/fur pigmentation, clothes they usually wear, overall cleanliness...","value":""},{"isEmpty":true,"label":"Psychology","placeholder":"How they think: motives, virtues, vices, flaws, attitude/behavior, sexuality...","value":""},{"isEmpty":true,"label":"Affiliations","placeholder":"Who they associate with and how they got involved...","value":""},{"isEmpty":true,"label":"Sociology","placeholder":"Describe how they interact with family, love interests, friends, strangers, mentors...","value":""},{"isEmpty":true,"label":"Perspective","placeholder":"Political views, religious ideas, interests, hobbies...","value":""},{"isEmpty":true,"label":"Journey","placeholder":"Where they started, what conflicts are encountered, how their character evolves...","value":""},{"isEmpty":true,"label":"History","placeholder":"What happened before the story started: where they were born, how they were raised and how it affected them, level of education they achieved, career path(s), suffered trauma...","value":""}],"lastName":"Psaudo","ledCultureIds":[],"ledOrgIds":["lvrb3sxp6aoedg5k"],"lens":{},"lifeStatus":"Alive","middleName":"","motivation":{"content":[{"attrs":{"textAlign":"left"},"content":[{"text":"faire de la saphirie-sanslogne la region la plus développé du monde. LIBERTE EGALITE, ET LIBERTE","type":"text"}],"type":"paragraph"}],"type":"doc"},"negTraits":"","noteIds":[],"order":0,"orgIds":["lvrb3sxp6aoedg5k"],"portraitCrop":null,"posTraits":"","residenceId":"grrk18g8t6e23zqj","residenceIds":["grrk18g8t6e23zqj"],"sceneAppearanceIds":[],"sceneNarrateIds":[],"speciesIds":["l288wu9k3k06bur3"],"stats":[{"label":"Date de naissance","value":""},{"label":"Height","value":"1m86"},{"label":"Eye color","value":"BLACK "},{"label":"Hair color","value":"oreille de chat"},{"label":"Ethnicity","value":"Sanslogniens pure souche"},{"label":"Ideology","value":"Libéral-Démocrate"}],"status":1,"tagIds":[],"text":{"content":[{"attrs":{"textAlign":"left"},"content":[{"text":"President Officiel de la région Sanslognienne et de l'union saphirico-sanslogniens. (il est bg)","type":"text"}],"type":"paragraph"}],"type":"doc"},"textPreview":"","thingIds":[],"title":"Sans Psaudo","type":"characters","updatedAt":1763929552746}